.gitignore
LICENSE
README.md
pyproject.toml
requirements.txt
setup.py
.github/ISSUE_TEMPLATE/bug_report.md
.github/ISSUE_TEMPLATE/feature_request.md
.github/workflows/ci.yml
libprobe/__init__.py
libprobe/asset.py
libprobe/check.py
libprobe/config.py
libprobe/exceptions.py
libprobe/logger.py
libprobe/probe.py
libprobe/protocol.py
libprobe/response.py
libprobe/severity.py
libprobe/utils.py
libprobe/version.py
libprobe.egg-info/PKG-INFO
libprobe.egg-info/SOURCES.txt
libprobe.egg-info/dependency_links.txt
libprobe.egg-info/requires.txt
libprobe.egg-info/top_level.txt
libprobe/net/__init__.py
libprobe/net/package.py
libprobe/net/protocol.py