Metadata-Version: 2.4
Name: libprobe
Version: 2.0.1
Summary: Library for building InfraSonar probes
Home-page: https://github.com/infrasonar/python-libprobe
Download-URL: https://github.com/infrasonar/python-libprobe/tarball/v2.0.1
Author: Cesbit
Author-email: info@cesbit.com
Keywords: monitoring,infrasonar,probe
Classifier: Intended Audience :: Developers
Classifier: Operating System :: OS Independent
Classifier: Programming Language :: Python :: 3.9
Classifier: Programming Language :: Python :: 3.10
Classifier: Programming Language :: Python :: 3.11
Classifier: Programming Language :: Python :: 3.12
Classifier: Programming Language :: Python :: 3 :: Only
Classifier: Topic :: Software Development :: Libraries :: Python Modules
Classifier: Topic :: Text Processing :: Linguistic
License-File: LICENSE
Requires-Dist: colorlog
Requires-Dist: msgpack
Requires-Dist: setproctitle
Requires-Dist: pyyaml
Requires-Dist: cryptography
Dynamic: author
Dynamic: author-email
Dynamic: classifier
Dynamic: description
Dynamic: description-content-type
Dynamic: download-url
Dynamic: home-page
Dynamic: keywords
Dynamic: license-file
Dynamic: requires-dist
Dynamic: summary
